{
  "tiles": [
    {
      "name": "Go",
      "group": "Special"
    },
    {
      "name": "Mediterranean Avenue",
      "price": 60,
      "rent": [
        2,
        10,
        30,
        90,
        160,
        250
      ],
      "housecost": 50,
      "group": "purple",
      "rgb": [75, 0, 130]
    },
    {
      "name": "Community Chest",
      "group": "Special"
    },
    {
      "name": "Baltic Avenue",
      "price": 60,
      "rent": [
        4,
        20,
        60,
        180,
        320,
        450
      ],
      "housecost": 50,
      "group": "purple",
      "rgb": [75, 0, 130]
    },
    {
      "name": "Income Tax",
      "group": "Special"
    },
    {
      "name": "Reading Railroad",
      "price": 200,
      "rent": [
        25,
        50,
        100,
        200
      ],
      "group": "Railroad"
    },
    {
      "name": "Oriental Avenue",
      "price": 100,
      "rent": [
        6,
        30,
        90,
        270,
        400,
        550
      ],
      "housecost": 50,
      "group": "lightblue",
      "rgb": [135, 206, 250]
    },
    {
      "name": "Chance",
      "group": "Special"
    },
    {
      "name": "Vermont Avenue",
      "price": 100,
      "rent": [
        6,
        30,
        90,
        270,
        400,
        550
      ],
      "housecost": 50,
      "group": "lightblue",
      "rgb": [135, 206, 250]
    },
    {
      "name": "Connecticut Avenue",
      "price": 120,
      "rent": [
        8,
        40,
        100,
        300,
        450,
        600
      ],
      "housecost": 50,
      "group": "lightblue",
      "rgb": [135, 206, 250]
    },
    {
      "name": "Jail / Just Visiting",
      "group": "Special"
    },
    {
      "name": "St. Charles Place",
      "price": 140,
      "rent": [
        10,
        50,
        150,
        450,
        625,
        750
      ],
      "housecost": 100,
      "group": "pink",
      "rgb": [255, 20, 147]
    },
    {
      "name": "Electric Company",
      "price": 150,
      "rent": [
        4,
        10
      ],
      "group": "Utility"
    },
    {
      "name": "States Avenue",
      "price": 140,
      "rent": [
        10,
        50,
        150,
        450,
        625,
        750
      ],
      "housecost": 100,
      "group": "pink",
      "rgb": [255, 20, 147]
    },
    {
      "name": "Virginia Avenue",
      "price": 160,
      "rent": [
        12,
        60,
        180,
        500,
        700,
        900
      ],
      "housecost": 100,
      "group": "pink",
      "rgb": [255, 20, 147]
    },
    {
      "name": "Pennsylvania Railroad",
      "price": 200,
      "rent": [
        25,
        50,
        100,
        200
      ],
      "group": "Railroad"
    },
    {
      "name": "St. James Place",
      "price": 180,
      "rent": [
        14,
        70,
        200,
        550,
        750,
        950
      ],
      "housecost": 100,
      "group": "orange",
      "rgb": [255, 165, 0]
    },
    {
      "name": "Community Chest",
      "group": "Special"
    },
    {
      "name": "Tennessee Avenue",
      "price": 180,
      "rent": [
        14,
        70,
        200,
        550,
        750,
        950
      ],
      "housecost": 100,
      "group": "orange",
      "rgb": [255, 165, 0]
    },
    {
      "name": "New York Avenue",
      "price": 200,
      "rent": [
        16,
        80,
        220,
        600,
        800,
        1000
      ],
      "housecost": 100,
      "group": "orange",
      "rgb": [255, 165, 0]
    },
    {
      "name": "Free Parking",
      "group": "Special"
    },
    {
      "name": "Kentucky Avenue",
      "price": 220,
      "rent": [
        18,
        90,
        250,
        700,
        875,
        1050
      ],
      "housecost": 150,
      "group": "red",
      "rgb": [255, 0, 0]
    },
    {
      "name": "Chance",
      "group": "Special"
    },
    {
      "name": "Indiana Avenue",
      "price": 220,
      "rent": [
        18,
        90,
        250,
        700,
        875,
        1050
      ],
      "housecost": 150,
      "group": "red",
      "rgb": [255, 0, 0]
    },
    {
      "name": "Illinois Avenue",
      "price": 240,
      "rent": [
        20,
        100,
        300,
        750,
        925,
        1100
      ],
      "housecost": 150,
      "group": "red",
      "rgb": [255, 0, 0]
    },    {
      "name": "B. & O. Railroad",
      "price": 200,
      "rent": [
        25,
        50,
        100,
        200
      ],
      "group": "Railroad"
    },
    {
      "name": "Atlantic Avenue",
      "price": 260,
      "rent": [
        22,
        110,
        330,
        800,
        975,
        1150
      ],
      "housecost": 150,
      "group": "yellow",
      "rgb": [255, 255, 0]
    },
    {
      "name": "Ventnor Avenue",
      "price": 260,
      "rent": [
        22,
        110,
        330,
        800,
        975,
        1150
      ],
      "housecost": 150,
      "group": "yellow",
      "rgb": [255, 255, 0]
    },
    {
      "name": "Water Works",
      "price": 150,
      "rent": [
        4,
        10
      ],
      "group": "Utility"
    },
    {
      "name": "Marvin Gardens",
      "price": 280,
      "rent": [
        22,
        120,
        360,
        850,
        1025,
        1200
      ],
      "housecost": 150,
      "group": "yellow",
      "rgb": [255, 255, 0]
    },
    {
      "name": "Go To Jail",
      "group": "Special"
    },
    {
      "name": "Pacific Avenue",
      "price": 300,
      "rent": [
        26,
        130,
        390,
        900,
        1100,
        1275
      ],
      "housecost": 200,
      "group": "green",
      "rgb": [0, 128, 0]
    },
    {
      "name": "North Carolina Avenue",
      "price": 300,
      "rent": [
        26,
        130,
        390,
        900,
        1100,
        1275
      ],
      "housecost": 200,
      "group": "green",
      "rgb": [0, 128, 0]
    },
    {
      "name": "Community Chest",
      "group": "Special"
    },
    {
      "name": "Pennsylvania Avenue",
      "price": 320,
      "rent": [
        28,
        150,
        450,
        1000,
        1200,
        1400
      ],
      "housecost": 200,
      "group": "green",
      "rgb": [0, 128, 0]
    },
    {
      "name": "Short Line Railroad",
      "price": 200,
      "rent": [
        25,
        50,
        100,
        200
      ],
      "group": "Railroad"
    },
    {
      "name": "Chance",
      "group": "Special"
    },
    {
      "name": "Park Place",
      "price": 350,
      "rent": [
        35,
        175,
        500,
        1100,
        1300,
        1500
      ],
      "housecost": 200,
      "group": "darkblue",
      "rgb": [0, 0, 139]
    },
    {
      "name": "Luxury Tax",
      "group": "Special"
    },
    {
      "name": "Boardwalk",
      "price": 400,
      "rent": [
        50,
        200,
        600,
        1400,
        1700,
        2000
      ],
      "housecost": 200,
      "group": "darkblue",
      "rgb": [0, 0, 139]
    }
  ],
  "chance": [
    {
      "title": "Advance to Go (Collect $200)",
      "action": "move",
      "destination": 0
    },
    {
      "title": "Advance to Illinois Avenue - If you pass Go, collect $200",
      "action": "move",
      "destination": 24
    },
    {
      "title": "Advance to St. Charles Place - If you pass Go, collect $200",
      "action": "move",
      "destination": 11
    },
    {
      "title": "Advance token to nearest Utility. If unowned, you may buy it from the Bank. If owned, throw dice and pay owner a total ten times the amount thrown.",
      "action": "movenearest",
      "group": "utility",
      "rentmultiplier": 10
    },
    {
      "title": "Advance token to the nearest Railroad and pay owner twice the rental to which he/she is otherwise entitled. If Railroad is unowned, you may buy it from the Bank.",
      "action": "movenearest",
      "group": "railroad",
      "rentmultiplier": 2
    },
    {
      "title": "Bank pays you dividend of $50",
      "action": "addfunds",
      "amount": 50
    },
    {
      "title": "Get out of Jail Free - This card may be kept until needed, or traded/sold",
      "action": "jail",
      "subaction": "getout"
    },
    {
      "title": "Go Back 3 Spaces",
      "action": "movespaces",
      "count": -3
    },
    {
      "title": "Go to Jail - Go directly to Jail - Do not pass Go, do not collect $200",
      "action": "jail",
      "subaction": "goto"
    },
    {
      "title": "Make general repairs on all your property - For each house pay $25 - For each hotel $100",
      "action": "propertycharges",
      "buildings": 25,
      "hotels": 100
    },
    {
      "title": "Pay poor tax of $15",
      "action": "addfunds",
      "amount": -15
    },
    {
      "title": "Take a trip to Reading Railroad - If you pass Go, collect $200",
      "action": "move",
      "destination": 5
    },
    {
      "title": "Take a walk on the Boardwalk - Advance token to Boardwalk",
      "action": "move",
      "destination": 39
    },
    {
      "title": "You have been elected Chairman of the Board - Pay each player $50",
      "action": "addfundstoplayers",
      "amount": 50
    },
    {
      "title": "Your building loan matures - Collect $150",
      "action": "addfunds",
      "amount": 50
    }
  ],
  "communitychest": [
    {
      "title": "Advance to Go (Collect $200)",
      "action": "move",
      "destination": 0
    },
    {
      "title": "Bank error in your favor - Collect $200 ",
      "action": "addfunds",
      "amount": 200
    },
    {
      "title": "Doctor fee - Pay $50",
      "action": "addfunds",
      "amount": -50
    },
    {
      "title": "From sale of stock you get $50",
      "action": "addfunds",
      "amount": 50
    },
    {
      "title": "Get Out of Jail Free",
      "action": "jail",
      "subaction": "getout"
    },
    {
      "title": "Go to Jail - Go directly to jail - Do not pass Go - Do not collect $200",
      "action": "jail",
      "subaction": "goto"
    },
    {
      "title": "Grand Opera Night - Collect $50 from every player for opening night seats",
      "action": "addfundsfromplayers",
      "amount": 50
    },
    {
      "title": "Holiday Fund matures - Receive $100",
      "action": "addfunds",
      "amount": 100
    },
    {
      "title": "Income tax refund - Collect $20",
      "action": "addfunds",
      "amount": 20
    },
    {
      "title": "Life insurance matures - Collect $100",
      "action": "addfunds",
      "amount": 100
    },
    {
      "title": "Pay hospital fees of $100",
      "action": "addfunds",
      "amount": -100
    },
    {
      "title": "Pay school fees of $150",
      "action": "addfunds",
      "amount": -150
    },
    {
      "title": "Receive $25 consultancy fee",
      "action": "addfunds",
      "amount": 25
    },
    {
      "title": "You are assessed for street repairs - $40 per house - $115 per hotel",
      "action": "propertycharges",
      "buildings": 40,
      "hotels": 115
    },
    {
      "title": "You have won second prize in a beauty contest - Collect $10",
      "action": "addfunds",
      "amount": 10
    },
    {
      "title": "You inherit $100",
      "action": "addfunds",
      "amount": 100
    }
  ]
}